TDLT/__init__.py
TDLT/trainer.py
TDLT/utils.py
TDLT_TQ-0.0.2.dist-info/LICENSE
TDLT_TQ-0.0.2.dist-info/METADATA
TDLT_TQ-0.0.2.dist-info/WHEEL
TDLT_TQ-0.0.2.dist-info/top_level.txt
TDLT_TQ-0.0.2.dist-info/RECORD
