Metadata-Version: 2.1
Name: TDLT-TQ
Version: 0.0.2
Summary: Tactful Deep Learning Tools
Home-page: https://github.com/pypa/sampleproject
Author: TianQi
Author-email: tianqi_729@163.com
License: UNKNOWN
Project-URL: Bug Tracker, https://github.com/pypa/sampleproject/issues
Platform: UNKNOWN
Classifier: Programming Language :: Python :: 3
Classifier: License :: OSI Approved :: MIT License
Classifier: Operating System :: OS Independent
Requires-Python: >=3.6
License-File: LICENSE
